shs_identification/__init__.py
shs_identification/shs_identification.py
shs_identification-1.3.dist-info/METADATA
shs_identification-1.3.dist-info/WHEEL
shs_identification-1.3.dist-info/top_level.txt
shs_identification-1.3.dist-info/RECORD
