Metadata-Version: 2.1
Name: shs-identification
Version: 1.3
Summary: UNKNOWN
Home-page: UNKNOWN
Author: UNKNOWN
Author-email: UNKNOWN
License: UNKNOWN
Platform: UNKNOWN
Requires-Dist: autopep8 (==1.5.6)
Requires-Dist: backcall (==0.2.0)
Requires-Dist: decorator (==4.4.2)
Requires-Dist: ipykernel (==5.5.3)
Requires-Dist: ipython (==7.22.0)
Requires-Dist: ipython-genutils (==0.2.0)
Requires-Dist: jedi (==0.18.0)
Requires-Dist: jupyter-client (==6.1.12)
Requires-Dist: jupyter-core (==4.7.1)
Requires-Dist: numpy (==1.20.2)
Requires-Dist: pandas (==1.2.3)
Requires-Dist: parso (==0.8.2)
Requires-Dist: pexpect (==4.8.0)
Requires-Dist: pickleshare (==0.7.5)
Requires-Dist: prompt-toolkit (==3.0.18)
Requires-Dist: ptyprocess (==0.7.0)
Requires-Dist: pycodestyle (==2.7.0)
Requires-Dist: Pygments (==2.8.1)
Requires-Dist: python-dateutil (==2.8.1)
Requires-Dist: pytz (==2021.1)
Requires-Dist: pyzmq (==22.0.3)
Requires-Dist: scipy (==1.6.2)
Requires-Dist: six (==1.15.0)
Requires-Dist: toml (==0.10.2)
Requires-Dist: tornado (==6.1)
Requires-Dist: traitlets (==5.0.5)
Requires-Dist: wcwidth (==0.2.5)
